{
    "data_hits": {
        "0": {
            "0": [
                595,
                287
            ],
            "1": [
                443,
                188
            ],
            "2": [
                545,
                251
            ],
            "3": [
                589,
                287
            ],
            "4": [
                594,
                332
            ],
            "5": [
                590,
                308
            ],
            "6": [
                528,
                303
            ],
            "7": [
                720,
                425
            ]
        },
        "1": {
            "0": [
                405,
                182
            ],
            "1": [
                534,
                260
            ],
            "2": [
                449,
                222
            ],
            "3": [
                1025,
                715
            ],
            "4": [
                502,
                254
            ],
            "5": [
                561,
                305
            ],
            "6": [
                609,
                344
            ],
            "7": [
                519,
                284
            ]
        },
        "2": {
            "0": [
                468,
                218
            ],
            "1": [
                516,
                253
            ],
            "2": [
                570,
                303
            ],
            "3": [
                576,
                326
            ],
            "4": [
                621,
                365
            ],
            "5": [
                556,
                313
            ],
            "6": [
                601,
                339
            ],
            "7": [
                696,
                412
            ]
        },
        "3": {
            "0": [
                581,
                327
            ],
            "1": [
                614,
                393
            ],
            "2": [
                654,
                383
            ],
            "3": [
                498,
                266
            ],
            "4": [
                476,
                255
            ],
            "5": [
                622,
                372
            ],
            "6": [
                566,
                323
            ],
            "7": [
                592,
                340
            ]
        },
        "4": {
            "0": [
                581,
                283
            ],
            "1": [
                543,
                281
            ],
            "2": [
                550,
                268
            ],
            "3": [
                566,
                309
            ],
            "4": [
                565,
                321
            ],
            "5": [
                532,
                277
            ],
            "6": [
                661,
                386
            ],
            "7": [
                605,
                311
            ]
        },
        "5": {
            "0": [
                510,
                242
            ],
            "1": [
                574,
                292
            ],
            "2": [
                538,
                282
            ],
            "3": [
                534,
                290
            ],
            "4": [
                617,
                359
            ],
            "5": [
                616,
                351
            ],
            "6": [
                589,
                332
            ],
            "7": [
                626,
                366
            ]
        },
        "6": {
            "0": [
                880,
                612
            ],
            "1": [
                677,
                425
            ],
            "2": [
                572,
                342
            ],
            "3": [
                404,
                219
            ],
            "4": [
                537,
                321
            ],
            "5": [
                467,
                245
            ],
            "6": [
                635,
                411
            ],
            "7": [
                432,
                240
            ]
        },
        "7": {
            "0": [
                580,
                364
            ],
            "1": [
                598,
                349
            ],
            "2": [
                579,
                334
            ],
            "3": [
                690,
                453
            ],
            "4": [
                559,
                332
            ],
            "5": [
                536,
                310
            ],
            "6": [
                601,
                372
            ],
            "7": [
                459,
                268
            ]
        },
        "8": {
            "0": [
                680,
                464
            ],
            "1": [
                833,
                594
            ],
            "2": [
                907,
                704
            ],
            "3": [
                632,
                431
            ],
            "4": [
                624,
                395
            ],
            "5": [
                357,
                180
            ],
            "6": [
                402,
                220
            ],
            "7": [
                168,
                92
            ]
        },
        "9": {
            "0": [
                529,
                341
            ],
            "1": [
                882,
                646
            ],
            "2": [
                703,
                494
            ],
            "3": [
                622,
                418
            ],
            "4": [
                385,
                197
            ],
            "5": [
                549,
                351
            ],
            "6": [
                472,
                303
            ],
            "7": [
                462,
                284
            ]
        },
        "10": {
            "0": [
                514,
                259
            ],
            "1": [
                498,
                274
            ],
            "2": [
                498,
                302
            ],
            "3": [
                567,
                357
            ],
            "4": [
                584,
                332
            ],
            "5": [
                915,
                661
            ],
            "6": [
                623,
                414
            ],
            "7": [
                405,
                188
            ]
        },
        "11": {
            "0": [
                671,
                418
            ],
            "1": [
                532,
                295
            ],
            "2": [
                478,
                263
            ],
            "3": [
                146,
                48
            ],
            "4": [
                639,
                394
            ],
            "5": [
                666,
                408
            ],
            "6": [
                778,
                532
            ],
            "7": [
                690,
                435
            ]
        },
        "12": {
            "0": [
                333,
                179
            ],
            "1": [
                441,
                273
            ],
            "2": [
                662,
                444
            ],
            "3": [
                544,
                332
            ],
            "4": [
                673,
                430
            ],
            "5": [
                849,
                612
            ],
            "6": [
                902,
                664
            ],
            "7": [
                200,
                104
            ]
        },
        "13": {
            "0": [
                431,
                207
            ],
            "1": [
                480,
                256
            ],
            "2": [
                436,
                227
            ],
            "3": [
                572,
                375
            ],
            "4": [
                762,
                480
            ],
            "5": [
                728,
                477
            ],
            "6": [
                623,
                378
            ],
            "7": [
                572,
                341
            ]
        },
        "14": {
            "0": [
                590,
                326
            ],
            "1": [
                716,
                431
            ],
            "2": [
                587,
                381
            ],
            "3": [
                604,
                330
            ],
            "4": [
                429,
                256
            ],
            "5": [
                502,
                279
            ],
            "6": [
                465,
                259
            ],
            "7": [
                711,
                448
            ]
        },
        "15": {
            "0": [
                503,
                239
            ],
            "1": [
                430,
                244
            ],
            "2": [
                615,
                353
            ],
            "3": [
                238,
                78
            ],
            "4": [
                850,
                543
            ],
            "5": [
                615,
                373
            ],
            "6": [
                818,
                538
            ],
            "7": [
                535,
                274
            ]
        },
        "16": {
            "0": [
                362,
                191
            ],
            "1": [
                514,
                295
            ],
            "2": [
                601,
                369
            ],
            "3": [
                770,
                523
            ],
            "4": [
                818,
                555
            ],
            "5": [
                408,
                210
            ],
            "6": [
                438,
                233
            ],
            "7": [
                693,
                466
            ]
        },
        "17": {
            "0": [
                539,
                261
            ],
            "1": [
                793,
                500
            ],
            "2": [
                657,
                368
            ],
            "3": [
                704,
                446
            ],
            "4": [
                680,
                397
            ],
            "5": [
                381,
                183
            ],
            "6": [
                584,
                353
            ],
            "7": [
                266,
                125
            ]
        },
        "18": {
            "0": [
                586,
                299
            ],
            "1": [
                388,
                178
            ],
            "2": [
                616,
                320
            ],
            "3": [
                754,
                445
            ],
            "4": [
                587,
                312
            ],
            "5": [
                484,
                249
            ],
            "6": [
                663,
                389
            ],
            "7": [
                526,
                269
            ]
        },
        "19": {
            "0": [
                531,
                282
            ],
            "1": [
                258,
                90
            ],
            "2": [
                604,
                336
            ],
            "3": [
                607,
                342
            ],
            "4": [
                724,
                423
            ],
            "5": [
                647,
                369
            ],
            "6": [
                680,
                407
            ],
            "7": [
                553,
                290
            ]
        },
        "20": {
            "0": [
                560,
                314
            ],
            "1": [
                442,
                233
            ],
            "2": [
                666,
                391
            ],
            "3": [
                737,
                502
            ],
            "4": [
                565,
                328
            ],
            "5": [
                635,
                376
            ],
            "6": [
                386,
                187
            ],
            "7": [
                613,
                376
            ]
        },
        "21": {
            "0": [
                530,
                279
            ],
            "1": [
                536,
                284
            ],
            "2": [
                607,
                355
            ],
            "3": [
                510,
                274
            ],
            "4": [
                562,
                330
            ],
            "5": [
                649,
                402
            ],
            "6": [
                686,
                443
            ],
            "7": [
                524,
                302
            ]
        },
        "22": {
            "0": [
                580,
                318
            ],
            "1": [
                594,
                347
            ],
            "2": [
                394,
                193
            ],
            "3": [
                636,
                386
            ],
            "4": [
                491,
                265
            ],
            "5": [
                639,
                377
            ],
            "6": [
                548,
                282
            ],
            "7": [
                722,
                458
            ]
        },
        "23": {
            "0": [
                340,
                172
            ],
            "1": [
                549,
                273
            ],
            "2": [
                702,
                429
            ],
            "3": [
                469,
                252
            ],
            "4": [
                633,
                378
            ],
            "5": [
                713,
                465
            ],
            "6": [
                590,
                316
            ],
            "7": [
                607,
                372
            ]
        },
        "24": {
            "0": [
                652,
                407
            ],
            "1": [
                457,
                239
            ],
            "2": [
                509,
                296
            ],
            "3": [
                495,
                274
            ],
            "4": [
                518,
                287
            ],
            "5": [
                568,
                324
            ],
            "6": [
                805,
                508
            ],
            "7": [
                600,
                365
            ]
        },
        "25": {
            "0": [
                498,
                257
            ],
            "1": [
                502,
                271
            ],
            "2": [
                589,
                346
            ],
            "3": [
                426,
                200
            ],
            "4": [
                590,
                319
            ],
            "5": [
                685,
                410
            ],
            "6": [
                684,
                418
            ],
            "7": [
                630,
                388
            ]
        },
        "26": {
            "0": [
                710,
                417
            ],
            "1": [
                550,
                272
            ],
            "2": [
                384,
                185
            ],
            "3": [
                587,
                311
            ],
            "4": [
                556,
                291
            ],
            "5": [
                643,
                394
            ],
            "6": [
                593,
                320
            ],
            "7": [
                581,
                307
            ]
        },
        "27": {
            "0": [
                646,
                365
            ],
            "1": [
                501,
                267
            ],
            "2": [
                496,
                243
            ],
            "3": [
                557,
                309
            ],
            "4": [
                564,
                311
            ],
            "5": [
                690,
                433
            ],
            "6": [
                735,
                498
            ],
            "7": [
                415,
                196
            ]
        },
        "28": {
            "0": [
                470,
                212
            ],
            "1": [
                725,
                429
            ],
            "2": [
                582,
                311
            ],
            "3": [
                435,
                203
            ],
            "4": [
                590,
                299
            ],
            "5": [
                552,
                275
            ],
            "6": [
                662,
                376
            ],
            "7": [
                587,
                344
            ]
        },
        "29": {
            "0": [
                600,
                290
            ],
            "1": [
                441,
                219
            ],
            "2": [
                607,
                323
            ],
            "3": [
                790,
                469
            ],
            "4": [
                666,
                363
            ],
            "5": [
                521,
                264
            ],
            "6": [
                620,
                360
            ],
            "7": [
                359,
                177
            ]
        },
        "30": {
            "0": [
                525,
                291
            ],
            "1": [
                710,
                447
            ],
            "2": [
                625,
                324
            ],
            "3": [
                818,
                527
            ],
            "4": [
                724,
                452
            ],
            "5": [
                338,
                170
            ],
            "6": [
                540,
                290
            ],
            "7": [
                324,
                139
            ]
        },
        "31": {
            "0": [
                577,
                286
            ],
            "1": [
                434,
                210
            ],
            "2": [
                326,
                175
            ],
            "3": [
                742,
                484
            ],
            "4": [
                768,
                472
            ],
            "5": [
                638,
                374
            ],
            "6": [
                731,
                480
            ],
            "7": [
                388,
                185
            ]
        }
    },
    "total_time": [
        335.6762731075287,
        374.91672539711,
        272.366685628891,
        317.9019618034363,
        381.5770847797394
    ],
    "total_num_tokens": [
        496,
        536,
        396,
        446,
        532
    ]
}